COPYING
LICENSE
MANIFEST.in
README.rst
setup.py
cmsplugin_markup_tracwiki/__init__.py
cmsplugin_markup_tracwiki/components.py
cmsplugin_markup_tracwiki/macros.py
cmsplugin_markup_tracwiki/models.py
cmsplugin_markup_tracwiki/tracwiki.py
cmsplugin_markup_tracwiki.egg-info/PKG-INFO
cmsplugin_markup_tracwiki.egg-info/SOURCES.txt
cmsplugin_markup_tracwiki.egg-info/dependency_links.txt
cmsplugin_markup_tracwiki.egg-info/not-zip-safe
cmsplugin_markup_tracwiki.egg-info/requires.txt
cmsplugin_markup_tracwiki.egg-info/top_level.txt
cmsplugin_markup_tracwiki/templatetags/__init__.py
cmsplugin_markup_tracwiki/templatetags/tracwiki.py
docs/Makefile
docs/conf.py
docs/index.rst