Metadata-Version: 1.1
Name: cmsplugin-markup-tracwiki
Version: 0.2.2
Summary: Trac wiki engine integration with Django CMS as a plugin for cmsplugin-markup.
Home-page: https://bitbucket.org/mitar/cmsplugin-markup-tracwiki
Author: Mitar
Author-email: mitar.django@tnode.com
License: AGPLv3
Platform: UNKNOWN
Classifier: Development Status :: 4 - Beta
Classifier: Environment :: Web Environment
Classifier: Intended Audience :: Developers
Classifier: License :: OSI Approved :: GNU Affero General Public License v3
Classifier: Operating System :: OS Independent
Classifier: Programming Language :: Python
Classifier: Framework :: Django
